Metadata-Version: 1.0
Name: hyhrm
Version: 0.1
Summary: A safe rm by mv
Home-page: https://github.com/huoyinghui
Author: hyhlinux
Author-email: django_hyh@163.com
License: UNKNOWN
Platform: UNKNOWN
